eversend/__init__.py
eversend/account.py
eversend/base.py
eversend/beneficiaries.py
eversend/collections.py
eversend/crypto.py
eversend/exchange.py
eversend/payouts.py
eversend/transactions.py
eversend/wallets.py
eversend/utils/__init__.py
eversend/utils/api.py
eversend/utils/exceptions.py
eversend-1.0.1.dist-info/LICENSE
eversend-1.0.1.dist-info/METADATA
eversend-1.0.1.dist-info/WHEEL
eversend-1.0.1.dist-info/top_level.txt
eversend-1.0.1.dist-info/RECORD
